{
    "jest":         { "png":"", "svg":"" },
    "karma":        { "png":"", "svg":"" },
    "jenkins":      { "png":"", "svg":"" },
    "jasmine":      { "png":"", "svg":"" },
    "kafka":        { "png":"https://github.com/bcd-kushal/Kushal-Kumar/assets/96081625/2aa400a2-0e3f-4ecc-a7a8-26f9de0c814c", "svg":"" },
    "appwrite":     { "png":"", "svg":"" },
    "babel":        { "png":"", "svg":"" },
    "bun":          { "png":"", "svg":"" },
    "websocket":    { "png":"", "svg":"" },
    "markdown":     { "png":"", "svg":"" },
    "arduino":      { "png":"", "svg":"" },
    "solr":         { "png":"", "svg":"" },
    "git":          { "png":"", "svg":"" }
}